topika/__init__.py
topika/channel.py
topika/common.py
topika/compat.py
topika/connection.py
topika/exceptions.py
topika/exchange.py
topika/message.py
topika/queue.py
topika/robust_channel.py
topika/robust_connection.py
topika/robust_exchange.py
topika/robust_queue.py
topika/tools.py
topika/transaction.py
topika/version.py
topika-0.2.2.dist-info/LICENSE
topika-0.2.2.dist-info/METADATA
topika-0.2.2.dist-info/WHEEL
topika-0.2.2.dist-info/top_level.txt
topika-0.2.2.dist-info/RECORD
